sbomtools/__init__.py
sbomtools/constants.py
sbomtools/cyclonedx.py
sbomtools/exceptions.py
sbomtools/grep.py
sbomtools/remove.py
sbomtools/sbomgrep.py
sbomtools/sbomls.py
sbomtools/sbomrm.py
sbomtools/sbomupdate.py
sbomtools/spdx.py
sbomtools/update.py
sbomtools-0.3.3.dist-info/LICENSE.txt
sbomtools-0.3.3.dist-info/METADATA
sbomtools-0.3.3.dist-info/WHEEL
sbomtools-0.3.3.dist-info/entry_points.txt
sbomtools-0.3.3.dist-info/top_level.txt
sbomtools-0.3.3.dist-info/RECORD
