Metadata-Version: 2.1
Name: sbomtools
Version: 0.3.3
Summary: SBOM tools
Home-page: https://github.com/sbomtools/sbomtools
Author: Eliot Lear
Author-email: lear@cisco.com
License: BSD 3-Clause License
Requires-Python: >=3.8
License-File: LICENSE.txt
